abb_assetvista_avtypes/__init__.py
abb_assetvista_avtypes/avlayerFunctions.py
abb_assetvista_avtypes/avlayerTypes.py
abb_assetvista_avtypes/edgeniusFunctions.py
abb_assetvista_avtypes/edgeniusTypes.py
avtypes/__init__.py
avtypes/avlayerFunctions.py
avtypes/avlayerTypes.py
avtypes/edgeniusFunctions.py
avtypes/edgeniusTypes.py
abb_assetvista_avtypes-0.1.0.dist-info/METADATA
abb_assetvista_avtypes-0.1.0.dist-info/WHEEL
abb_assetvista_avtypes-0.1.0.dist-info/top_level.txt
abb_assetvista_avtypes-0.1.0.dist-info/RECORD
